wtfl/__init__.py
wtfl/grammar.py
wtfl/internal_types.py
wtfl/parser.py
wtfl/reader.py
wtfl/writer.py
wtfl-1.2.1.dist-info/LICENSE
wtfl-1.2.1.dist-info/METADATA
wtfl-1.2.1.dist-info/WHEEL
wtfl-1.2.1.dist-info/RECORD
