Metadata-Version: 2.1
Name: wtfl
Version: 1.2.1
Summary: Well-designed Text-based Friendly Language
Home-page: https://github.com/evtn/wtfl
License: MIT
Keywords: markup,config
Author: Dmitry Gritsenko
Author-email: k01419q45@ya.ru
Requires-Python: >=3.7,<4.0
Classifier: License :: OSI Approved :: MIT License
Classifier: Programming Language :: Python :: 3
Classifier: Programming Language :: Python :: 3.7
Classifier: Programming Language :: Python :: 3.8
Classifier: Programming Language :: Python :: 3.9
Classifier: Programming Language :: Python :: 3.10
Classifier: Programming Language :: Python :: 3.11
Requires-Dist: lark (>=1.1.5,<2.0.0)
Requires-Dist: lark-dynamic (>=1.0.4,<2.0.0)
Requires-Dist: typing-extensions (>=4.5.0,<5.0.0)
Project-URL: Repository, https://github.com/evtn/wtfl
